__init__.py
vectorcheck/__init__.py
vectorcheck/loader.py
vectorcheck/main.py
vectorcheck/reporter.py
vectorcheck/runner.py
vectorcheck/source.py
vectorcheck-0.1.0.dist-info/METADATA
vectorcheck-0.1.0.dist-info/WHEEL
vectorcheck-0.1.0.dist-info/entry_points.txt
vectorcheck-0.1.0.dist-info/top_level.txt
vectorcheck-0.1.0.dist-info/RECORD
