Metadata-Version: 2.4
Name: vectorcheck
Version: 0.1.0
Summary: AI Native Testing Framework for VectorWave
Requires-Python: >=3.10
Requires-Dist: typer>=0.9.0
Requires-Dist: rich>=13.0.0
Requires-Dist: pydantic>=2.0.0
Requires-Dist: vectorwave
